{
  "id": "rocket-dog-warrior",
  "name": "Rocket Dog",
  "class": "Warrior",
  "stars": 4,
  "eddie": false,
  "awakenable": false,
  "talismans": "SWW...",
  "talismansSet": "5w 4w 4s",
  "url": "http://www.news.maiden-lotb.com/n3/character-en/rocket-dog-warrior/",
  "image": "http://www.news.maiden-lotb.com/n3/wp-content/uploads/2020/06/missing_batch_0003_Layer-4.png",
  "skills": [
    {
      "name": "WAR MACHINE",
      "typeName": "Present Basic Attack",
      "type": "Basic",
      "desc": [
        "• Deals physical damage to all enemies.",
        "• 45% Chance to inflict Bleed for 2 turns.",
        "• Bleed deals true damage over time with a chance to Heal Block every turn."
      ]
    },
    {
      "name": "TACKLE\n",
      "typeName": "Present Power Attack",
      "type": "Power",
      "desc": [
        "• Deals true damage to a single target.",
        "• 45% Chance to Remove Beneficial Effects.",
        "• 35% Chance to Stun for 2 turns.",
        "• Instantly Gain an Extra Turn.",
        "• Damage increases based on your MAX HP."
      ],
      "powerCost": 3
    },
    {
      "name": "BLOOD THIRST\n",
      "typeName": "Passive",
      "type": "Passive",
      "desc": [
        "• Grants Lifesteal status to all allies at the start of battle.",
        "• Lifesteal heals you for 60% of the physical damage you deal.."
      ]
    }
  ]
}